aw_agents/__init__.py
aw_agents/base.py
aw_agents/adapters/__init__.py
aw_agents/adapters/mcp.py
aw_agents/adapters/openapi.py
aw_agents/download/__init__.py
aw_agents/download/agent.py
aw_agents/download/download_core.py
aw_agents-0.1.0.dist-info/licenses/LICENSE
aw_agents-0.1.0.dist-info/METADATA
aw_agents-0.1.0.dist-info/WHEEL
aw_agents-0.1.0.dist-info/top_level.txt
aw_agents-0.1.0.dist-info/RECORD
