Metadata-Version: 2.4
Name: aw-agents
Version: 0.1.0
Summary: AI agents for agentic workflows, deployable to multiple chatbot platforms
Home-page: https://github.com/thorwhalen/aw_agents
Author: Thor Whalen
Author-email: Your Name <your.email@example.com>
License: MIT
Project-URL: Homepage, https://github.com/yourusername/aw-agents
Project-URL: Documentation, https://github.com/yourusername/aw-agents#readme
Project-URL: Repository, https://github.com/yourusername/aw-agents
Project-URL: Issues, https://github.com/yourusername/aw-agents/issues
Keywords: ai,agents,chatbots,mcp,openapi,claude,chatgpt
Platform: any
Classifier: Development Status :: 3 - Alpha
Classifier: Intended Audience :: Developers
Classifier: License :: OSI Approved :: MIT License
Classifier: Programming Language :: Python :: 3
Classifier: Programming Language :: Python :: 3.9
Classifier: Programming Language :: Python :: 3.10
Classifier: Programming Language :: Python :: 3.11
Classifier: Programming Language :: Python :: 3.12
Requires-Python: >=3.9
License-File: LICENSE
Requires-Dist: requests>=2.31.0
Requires-Dist: beautifulsoup4>=4.12.0
Requires-Dist: graze>=0.1.0
Provides-Extra: mcp
Requires-Dist: mcp>=0.1.0; extra == "mcp"
Provides-Extra: api
Requires-Dist: fastapi>=0.109.0; extra == "api"
Requires-Dist: uvicorn[standard]>=0.27.0; extra == "api"
Requires-Dist: pydantic>=2.5.0; extra == "api"
Provides-Extra: all
Requires-Dist: aw-agents[api,mcp]; extra == "all"
Provides-Extra: dev
Requires-Dist: pytest>=7.0.0; extra == "dev"
Requires-Dist: pytest-cov>=4.0.0; extra == "dev"
Requires-Dist: black>=23.0.0; extra == "dev"
Requires-Dist: mypy>=1.0.0; extra == "dev"
Requires-Dist: ruff>=0.1.0; extra == "dev"
Dynamic: license-file
